markovm.py
markovm-0.1.0.dist-info/LICENSE
markovm-0.1.0.dist-info/METADATA
markovm-0.1.0.dist-info/WHEEL
markovm-0.1.0.dist-info/top_level.txt
markovm-0.1.0.dist-info/RECORD
