Metadata-Version: 2.1
Name: markovm
Version: 0.1.0
Summary: Python library for Markov Models.
Author-email: HH-MWB <h.hong@mail.com>
License: MIT
Project-URL: Homepage, https://pypi.org/project/markovm
Project-URL: Bug Reports, https://github.com/HH-MWB/markovm/issues
Project-URL: Source, https://github.com/HH-MWB/markovm
Keywords: markov model,markov chain
Classifier: Development Status :: 2 - Pre-Alpha
Classifier: Intended Audience :: Developers
Classifier: License :: OSI Approved :: MIT License
Classifier: Programming Language :: Python
Classifier: Programming Language :: Python :: 3.7
Classifier: Programming Language :: Python :: 3.8
Classifier: Programming Language :: Python :: 3.9
Classifier: Programming Language :: Python :: 3.10
Classifier: Programming Language :: Python :: 3.11
Classifier: Operating System :: OS Independent
Requires-Python: >=3.7
License-File: LICENSE
Requires-Dist: numpy (~=1.20)
